odoo/addons/account_mass_reconcile_by_sale_line/README.rst
odoo/addons/account_mass_reconcile_by_sale_line/__init__.py
odoo/addons/account_mass_reconcile_by_sale_line/__manifest__.py
odoo/addons/account_mass_reconcile_by_sale_line/i18n/account_mass_reconcile_by_sale_line.pot
odoo/addons/account_mass_reconcile_by_sale_line/i18n/es.po
odoo/addons/account_mass_reconcile_by_sale_line/i18n/it.po
odoo/addons/account_mass_reconcile_by_sale_line/i18n/sv.po
odoo/addons/account_mass_reconcile_by_sale_line/models/__init__.py
odoo/addons/account_mass_reconcile_by_sale_line/models/advanced_reconciliation.py
odoo/addons/account_mass_reconcile_by_sale_line/models/base_advanced_reconciliation.py
odoo/addons/account_mass_reconcile_by_sale_line/models/mass_reconcile.py
odoo/addons/account_mass_reconcile_by_sale_line/readme/CONTRIBUTORS.rst
odoo/addons/account_mass_reconcile_by_sale_line/readme/DESCRIPTION.rst
odoo/addons/account_mass_reconcile_by_sale_line/readme/USAGE.rst
odoo/addons/account_mass_reconcile_by_sale_line/security/ir.model.access.csv
odoo/addons/account_mass_reconcile_by_sale_line/static/description/icon.png
odoo/addons/account_mass_reconcile_by_sale_line/static/description/index.html
odoo/addons/account_mass_reconcile_by_sale_line/views/mass_reconcile.xml
odoo14_addon_account_mass_reconcile_by_sale_line-14.0.1.0.1.dev11.dist-info/METADATA
odoo14_addon_account_mass_reconcile_by_sale_line-14.0.1.0.1.dev11.dist-info/WHEEL
odoo14_addon_account_mass_reconcile_by_sale_line-14.0.1.0.1.dev11.dist-info/top_level.txt
odoo14_addon_account_mass_reconcile_by_sale_line-14.0.1.0.1.dev11.dist-info/RECORD
